moomin.py
setup.py
moomin.egg-info/PKG-INFO
moomin.egg-info/SOURCES.txt
moomin.egg-info/dependency_links.txt
moomin.egg-info/requires.txt
moomin.egg-info/top_level.txt
scripts/moomin