Metadata-Version: 1.0
Name: moomin
Version: 0.1.0
Summary: Moinmoin client
Home-page: https://github.com/tototoshi/moomin
Author: Toshiyuki Takahashi
Author-email: t.toshi.0412 at gmail.com
License: BSD
Keywords: MoinMoin
Platform: POSIX
Platform: Windows
Classifier: License :: OSI Approved :: BSD License
Classifier: Programming Language :: Python
Classifier: Development Status :: 4 - Beta
Classifier: Environment :: Console
Classifier: Intended Audience :: Developers
Classifier: Topic :: Utilities 
